ln.py
ln.py-1.0.0.dist-info/entry_points.txt
ln.py-1.0.0.dist-info/LICENSE
ln.py-1.0.0.dist-info/WHEEL
ln.py-1.0.0.dist-info/METADATA
ln.py-1.0.0.dist-info/RECORD
