Metadata-Version: 2.1
Name: ln.py
Version: 1.0.0
Summary: symlinks made easier
Home-page: https://github.com/dmerejkowsky/ln.py
License: MIT
Author: Dimitri Merejkowsky
Author-email: d.merej@gmail.com
Requires-Python: >=3.6,<4.0
Classifier: Environment :: Console
Classifier: License :: OSI Approved :: MIT License
Classifier: Programming Language :: Python :: 3
Classifier: Programming Language :: Python :: 3.6
Classifier: Programming Language :: Python :: 3.7
Classifier: Programming Language :: Python :: 3.8
Classifier: Topic :: System :: Shells
Project-URL: Repository, https://github.com/dmerejkowsky/ln.py
